Metadata-Version: 2.4
Name: seqseg
Version: 1.0.1
Summary: A deep learning-based medical image blood vessel tracking and segmentation tool.
Author-email: Numi Sveinsson Cepero <numi@berkeley.com>
License: Apache-2.0
Project-URL: homepage, https://github.com/numisveinsson/SeqSeg
Project-URL: repository, https://github.com/numisveinsson/SeqSeg
Keywords: segmentation,deep learning,medical imaging,nnunet,medical image analysis,medical image segmentation,nnU-Net,blood vessel segmentation,vascular segmentation,vascular tracking,seqseg
Classifier: Programming Language :: Python :: 3
Classifier: License :: OSI Approved :: Apache Software License
Classifier: Operating System :: OS Independent
Classifier: Intended Audience :: Science/Research
Classifier: Intended Audience :: Healthcare Industry
Classifier: Topic :: Scientific/Engineering :: Artificial Intelligence
Classifier: Topic :: Scientific/Engineering :: Image Recognition
Classifier: Topic :: Scientific/Engineering :: Medical Science Apps.
Requires-Python: >=3.11
License-File: LICENSE
Requires-Dist: vtk
Requires-Dist: SimpleITK
Requires-Dist: PyYAML
Requires-Dist: nnunetv2
Provides-Extra: dev
Requires-Dist: pytest; extra == "dev"
Requires-Dist: some-other-dev-tools; extra == "dev"
Dynamic: license-file
